pybluebolt/__init__.py
pybluebolt/const.py
pybluebolt-0.0.1.dist-info/LICENSE.md
pybluebolt-0.0.1.dist-info/METADATA
pybluebolt-0.0.1.dist-info/WHEEL
pybluebolt-0.0.1.dist-info/top_level.txt
pybluebolt-0.0.1.dist-info/zip-safe
pybluebolt-0.0.1.dist-info/RECORD
