Metadata-Version: 2.1
Name: pybluebolt
Version: 0.0.1
Summary: Python interface for BlueBOLT API
Home-page: https://github.com/rsnodgrass/pybluebolt
Author: Ryan Snodgrass
Author-email: rsnodgrass@gmail.com
License: Apache Software License
Keywords: flo,home automation,water monitoring
Platform: UNKNOWN
Classifier: Programming Language :: Python :: 3
Classifier: License :: OSI Approved :: Apache Software License
Classifier: Operating System :: OS Independent
Requires-Dist: requests (>=2.0)
